CHANGES.rst
DESCRIPTION.rst
LICENSE
MANIFEST.in
README.md
setup.py
src/simflow/__init__.py
src/simflow/base.py
src/simflow/container.py
src/simflow/control.py
src/simflow/conversion.py
src/simflow/sink.py
src/simflow/source.py
src/simflow/transformer.py
src/simple_data_flow.egg-info/PKG-INFO
src/simple_data_flow.egg-info/SOURCES.txt
src/simple_data_flow.egg-info/dependency_links.txt
src/simple_data_flow.egg-info/requires.txt
src/simple_data_flow.egg-info/top_level.txt