Metadata-Version: 2.1
Name: simple-data-flow
Version: 0.0.1
Summary: This library provides basic building blocks for creating and executing simple workflows.
Home-page: https://github.com/fracpete/simple-data-flow
Author: Peter "fracpete" Reutemann
Author-email: simple-flow@fracpete.org
License: MIT
Classifier: Development Status :: 4 - Beta
Classifier: License :: OSI Approved :: MIT License
Classifier: Topic :: Software Development
Classifier: Programming Language :: Python :: 3
License-File: LICENSE
